[
  {
    "player": "Darren Waller",
    "team": "Dolphins",
    "opponent": "Ravens",
    "metric": 1.3
  },
  {
    "player": "Jake Ferguson",
    "team": "Cowboys",
    "opponent": "Cardinals",
    "metric": 1.2
  },
  {
    "player": "David Martin-Robinson",
    "team": "Titans",
    "opponent": "Chargers",
    "metric": 1.0
  },
  {
    "player": "Tucker Kraft",
    "team": "Packers",
    "opponent": "Panthers",
    "metric": 1.0
  },
  {
    "player": "AJ Barner",
    "team": "Seahawks",
    "opponent": "Commanders",
    "metric": 0.8
  },
  {
    "player": "Jake Tonges",
    "team": "49ers",
    "opponent": "Giants",
    "metric": 0.8
  },
  {
    "player": "Theo Johnson",
    "team": "Giants",
    "opponent": "49ers",
    "metric": 0.8
  },
  {
    "player": "Trey McBride",
    "team": "Cardinals",
    "opponent": "Cowboys",
    "metric": 0.8
  },
  {
    "player": "Pat Freiermuth",
    "team": "Steelers",
    "opponent": "Colts",
    "metric": 0.7
  },
  {
    "player": "Tyler Warren",
    "team": "Colts",
    "opponent": "Steelers",
    "metric": 0.6
  },
  {
    "player": "Brock Wright",
    "team": "Lions",
    "opponent": "Vikings",
    "metric": 0.5
  },
  {
    "player": "Connor Heyward",
    "team": "Steelers",
    "opponent": "Colts",
    "metric": 0.5
  },
  {
    "player": "George Kittle",
    "team": "49ers",
    "opponent": "Giants",
    "metric": 0.5
  },
  {
    "player": "Michael Mayer",
    "team": "Raiders",
    "opponent": "Jaguars",
    "metric": 0.5
  },
  {
    "player": "Mitchell Evans",
    "team": "Panthers",
    "opponent": "Packers",
    "metric": 0.5
  },
  {
    "player": "Sam LaPorta",
    "team": "Lions",
    "opponent": "Vikings",
    "metric": 0.5
  },
  {
    "player": "Tanner Hudson",
    "team": "Bengals",
    "opponent": "Bears",
    "metric": 0.5
  },
  {
    "player": "Terrance Ferguson",
    "team": "Rams",
    "opponent": "Saints",
    "metric": 0.5
  },
  {
    "player": "Hunter Henry",
    "team": "Patriots",
    "opponent": "Falcons",
    "metric": 0.4
  },
  {
    "player": "Oronde Gadsden II",
    "team": "Chargers",
    "opponent": "Titans",
    "metric": 0.4
  },
  {
    "player": "Travis Kelce",
    "team": "Chiefs",
    "opponent": "Bills",
    "metric": 0.4
  },
  {
    "player": "Zach Ertz",
    "team": "Commanders",
    "opponent": "Seahawks",
    "metric": 0.4
  },
  {
    "player": "Austin Hooper",
    "team": "Patriots",
    "opponent": "Falcons",
    "metric": 0.3
  },
  {
    "player": "Charlie Kolar",
    "team": "Ravens",
    "opponent": "Dolphins",
    "metric": 0.3
  },
  {
    "player": "Dalton Kincaid",
    "team": "Bills",
    "opponent": "Chiefs",
    "metric": 0.3
  },
  {
    "player": "Daniel Bellinger",
    "team": "Giants",
    "opponent": "49ers",
    "metric": 0.3
  },
  {
    "player": "Darnell Washington",
    "team": "Steelers",
    "opponent": "Colts",
    "metric": 0.3
  },
  {
    "player": "Dawson Knox",
    "team": "Bills",
    "opponent": "Chiefs",
    "metric": 0.3
  },
  {
    "player": "Hunter Long",
    "team": "Jaguars",
    "opponent": "Raiders",
    "metric": 0.3
  },
  {
    "player": "Jonnu Smith",
    "team": "Steelers",
    "opponent": "Colts",
    "metric": 0.3
  },
  {
    "player": "Josh Oliver",
    "team": "Vikings",
    "opponent": "Lions",
    "metric": 0.3
  },
  {
    "player": "Kyle Pitts Sr.",
    "team": "Falcons",
    "opponent": "Patriots",
    "metric": 0.3
  },
  {
    "player": "Noah Fant",
    "team": "Bengals",
    "opponent": "Bears",
    "metric": 0.3
  },
  {
    "player": "Tyler Higbee",
    "team": "Rams",
    "opponent": "Saints",
    "metric": 0.3
  },
  {
    "player": "Evan Engram",
    "team": "Broncos",
    "opponent": "Texans",
    "metric": 0.2
  },
  {
    "player": "Gunnar Helm",
    "team": "Titans",
    "opponent": "Chargers",
    "metric": 0.2
  },
  {
    "player": "Nate Adkins",
    "team": "Broncos",
    "opponent": "Texans",
    "metric": 0.2
  },
  {
    "player": "Tommy Tremble",
    "team": "Panthers",
    "opponent": "Packers",
    "metric": 0.2
  },
  {
    "player": "Adam Trautman",
    "team": "Broncos",
    "opponent": "Texans",
    "metric": 0.0
  },
  {
    "player": "Albert Okwuegbunam Jr.",
    "team": "Raiders",
    "opponent": "Jaguars",
    "metric": 0.0
  }
]