[
  {
    "player": "Puka Nacua",
    "team": "Rams",
    "opponent": "49ers",
    "metric": 15.0
  },
  {
    "player": "Quentin Johnston",
    "team": "Chargers",
    "opponent": "Commanders",
    "metric": 11.5
  },
  {
    "player": "Garrett Wilson",
    "team": "Jets",
    "opponent": "Cowboys",
    "metric": 10.5
  },
  {
    "player": "Chris Olave",
    "team": "Saints",
    "opponent": "Giants",
    "metric": 10.0
  },
  {
    "player": "George Pickens",
    "team": "Cowboys",
    "opponent": "Jets",
    "metric": 10.0
  },
  {
    "player": "A.J. Brown",
    "team": "Eagles",
    "opponent": "Broncos",
    "metric": 9.5
  },
  {
    "player": "Emeka Egbuka",
    "team": "Buccaneers",
    "opponent": "Seahawks",
    "metric": 9.0
  },
  {
    "player": "Justin Jefferson",
    "team": "Vikings",
    "opponent": "Browns",
    "metric": 9.0
  },
  {
    "player": "Keenan Allen",
    "team": "Chargers",
    "opponent": "Commanders",
    "metric": 9.0
  },
  {
    "player": "Nico Collins",
    "team": "Texans",
    "opponent": "Ravens",
    "metric": 8.5
  },
  {
    "player": "Marvin Harrison Jr.",
    "team": "Cardinals",
    "opponent": "Titans",
    "metric": 8.0
  },
  {
    "player": "Michael Pittman Jr.",
    "team": "Colts",
    "opponent": "Raiders",
    "metric": 8.0
  },
  {
    "player": "Mike Evans",
    "team": "Buccaneers",
    "opponent": "Seahawks",
    "metric": 8.0
  },
  {
    "player": "Ricky Pearsall",
    "team": "49ers",
    "opponent": "Rams",
    "metric": 8.0
  },
  {
    "player": "Tetairoa McMillan",
    "team": "Panthers",
    "opponent": "Dolphins",
    "metric": 8.0
  },
  {
    "player": "Tyreek Hill",
    "team": "Dolphins",
    "opponent": "Panthers",
    "metric": 8.0
  },
  {
    "player": "Xavier Worthy",
    "team": "Chiefs",
    "opponent": "Jaguars",
    "metric": 8.0
  },
  {
    "player": "Amon-Ra St. Brown",
    "team": "Lions",
    "opponent": "Bengals",
    "metric": 7.5
  },
  {
    "player": "Courtland Sutton",
    "team": "Broncos",
    "opponent": "Eagles",
    "metric": 7.0
  },
  {
    "player": "Davante Adams",
    "team": "Rams",
    "opponent": "49ers",
    "metric": 7.0
  },
  {
    "player": "Ja'Marr Chase",
    "team": "Bengals",
    "opponent": "Lions",
    "metric": 7.0
  },
  {
    "player": "Jerry Jeudy",
    "team": "Browns",
    "opponent": "Vikings",
    "metric": 7.0
  },
  {
    "player": "Brian Thomas Jr.",
    "team": "Jaguars",
    "opponent": "Chiefs",
    "metric": 6.5
  },
  {
    "player": "Ladd McConkey",
    "team": "Chargers",
    "opponent": "Commanders",
    "metric": 6.5
  },
  {
    "player": "Parker Washington",
    "team": "Jaguars",
    "opponent": "Chiefs",
    "metric": 6.5
  },
  {
    "player": "Christian Kirk",
    "team": "Texans",
    "opponent": "Ravens",
    "metric": 6.0
  },
  {
    "player": "Elic Ayomanor",
    "team": "Titans",
    "opponent": "Cardinals",
    "metric": 6.0
  },
  {
    "player": "Jalen Tolbert",
    "team": "Cowboys",
    "opponent": "Jets",
    "metric": 6.0
  },
  {
    "player": "Jaylen Waddle",
    "team": "Dolphins",
    "opponent": "Panthers",
    "metric": 6.0
  },
  {
    "player": "Troy Franklin",
    "team": "Broncos",
    "opponent": "Eagles",
    "metric": 6.0
  },
  {
    "player": "DeVonta Smith",
    "team": "Eagles",
    "opponent": "Broncos",
    "metric": 5.5
  },
  {
    "player": "Hollywood Brown",
    "team": "Chiefs",
    "opponent": "Jaguars",
    "metric": 5.5
  },
  {
    "player": "Jakobi Meyers",
    "team": "Raiders",
    "opponent": "Colts",
    "metric": 5.5
  },
  {
    "player": "Jameson Williams",
    "team": "Lions",
    "opponent": "Bengals",
    "metric": 5.5
  },
  {
    "player": "Jaxon Smith-Njigba",
    "team": "Seahawks",
    "opponent": "Buccaneers",
    "metric": 5.5
  },
  {
    "player": "Rashid Shaheed",
    "team": "Saints",
    "opponent": "Giants",
    "metric": 5.5
  },
  {
    "player": "Tre Tucker",
    "team": "Raiders",
    "opponent": "Colts",
    "metric": 5.5
  },
  {
    "player": "Tyquan Thornton",
    "team": "Chiefs",
    "opponent": "Jaguars",
    "metric": 5.5
  },
  {
    "player": "Zay Flowers",
    "team": "Ravens",
    "opponent": "Texans",
    "metric": 5.5
  },
  {
    "player": "Alec Pierce",
    "team": "Colts",
    "opponent": "Raiders",
    "metric": 5.0
  }
]