[
  {
    "player": "Tutu Atwell",
    "team": "Rams",
    "opponent": "Ravens",
    "metric": 31.0
  },
  {
    "player": "Jameson Williams",
    "team": "Lions",
    "opponent": "Chiefs",
    "metric": 26.1
  },
  {
    "player": "Luke McCaffrey",
    "team": "Commanders",
    "opponent": "Bears",
    "metric": 24.6
  },
  {
    "player": "Dareke Young",
    "team": "Seahawks",
    "opponent": "Jaguars",
    "metric": 24.0
  },
  {
    "player": "Devontez Walker",
    "team": "Ravens",
    "opponent": "Rams",
    "metric": 23.5
  },
  {
    "player": "Elijah Moore",
    "team": "Bills",
    "opponent": "Falcons",
    "metric": 23.0
  },
  {
    "player": "Malik Heath",
    "team": "Packers",
    "opponent": "Bengals",
    "metric": 23.0
  },
  {
    "player": "Calvin Ridley",
    "team": "Titans",
    "opponent": "Raiders",
    "metric": 21.8
  },
  {
    "player": "Tyquan Thornton",
    "team": "Chiefs",
    "opponent": "Lions",
    "metric": 21.2
  },
  {
    "player": "Nikko Remigio",
    "team": "Chiefs",
    "opponent": "Lions",
    "metric": 21.0
  },
  {
    "player": "Ashton Dulin",
    "team": "Colts",
    "opponent": "Cardinals",
    "metric": 19.3
  },
  {
    "player": "Casey Washington",
    "team": "Falcons",
    "opponent": "Bills",
    "metric": 19.0
  },
  {
    "player": "Rome Odunze",
    "team": "Bears",
    "opponent": "Commanders",
    "metric": 18.8
  },
  {
    "player": "George Pickens",
    "team": "Cowboys",
    "opponent": "Panthers",
    "metric": 18.1
  },
  {
    "player": "KaVontae Turpin",
    "team": "Cowboys",
    "opponent": "Panthers",
    "metric": 17.9
  },
  {
    "player": "Emeka Egbuka",
    "team": "Buccaneers",
    "opponent": "49ers",
    "metric": 17.5
  },
  {
    "player": "Brian Thomas Jr.",
    "team": "Jaguars",
    "opponent": "Seahawks",
    "metric": 17.4
  },
  {
    "player": "Terry McLaurin",
    "team": "Commanders",
    "opponent": "Bears",
    "metric": 17.2
  },
  {
    "player": "Jaxon Smith-Njigba",
    "team": "Seahawks",
    "opponent": "Jaguars",
    "metric": 17.1
  },
  {
    "player": "Davante Adams",
    "team": "Rams",
    "opponent": "Ravens",
    "metric": 17.0
  },
  {
    "player": "DeAndre Hopkins",
    "team": "Ravens",
    "opponent": "Rams",
    "metric": 17.0
  },
  {
    "player": "Jake Bobo",
    "team": "Seahawks",
    "opponent": "Jaguars",
    "metric": 17.0
  },
  {
    "player": "Alec Pierce",
    "team": "Colts",
    "opponent": "Cardinals",
    "metric": 16.9
  },
  {
    "player": "Andrei Iosivas",
    "team": "Bengals",
    "opponent": "Packers",
    "metric": 16.8
  },
  {
    "player": "Demarcus Robinson",
    "team": "49ers",
    "opponent": "Buccaneers",
    "metric": 16.5
  },
  {
    "player": "Rashid Shaheed",
    "team": "Saints",
    "opponent": "Patriots",
    "metric": 16.0
  },
  {
    "player": "Marvin Harrison Jr.",
    "team": "Cardinals",
    "opponent": "Colts",
    "metric": 15.9
  },
  {
    "player": "Travis Hunter",
    "team": "Jaguars",
    "opponent": "Seahawks",
    "metric": 15.9
  },
  {
    "player": "Kayshon Boutte",
    "team": "Patriots",
    "opponent": "Saints",
    "metric": 15.6
  },
  {
    "player": "Quentin Johnston",
    "team": "Chargers",
    "opponent": "Dolphins",
    "metric": 15.2
  },
  {
    "player": "Tetairoa McMillan",
    "team": "Panthers",
    "opponent": "Cowboys",
    "metric": 15.1
  },
  {
    "player": "Jauan Jennings",
    "team": "49ers",
    "opponent": "Buccaneers",
    "metric": 14.9
  },
  {
    "player": "Joshua Palmer",
    "team": "Bills",
    "opponent": "Falcons",
    "metric": 14.8
  },
  {
    "player": "DK Metcalf",
    "team": "Steelers",
    "opponent": "Browns",
    "metric": 14.2
  },
  {
    "player": "Jaylen Waddle",
    "team": "Dolphins",
    "opponent": "Chargers",
    "metric": 13.9
  },
  {
    "player": "Drake London",
    "team": "Falcons",
    "opponent": "Bills",
    "metric": 13.7
  },
  {
    "player": "Isaac TeSlaa",
    "team": "Lions",
    "opponent": "Chiefs",
    "metric": 13.7
  },
  {
    "player": "Courtland Sutton",
    "team": "Broncos",
    "opponent": "Jets",
    "metric": 13.6
  },
  {
    "player": "Elic Ayomanor",
    "team": "Titans",
    "opponent": "Raiders",
    "metric": 13.6
  },
  {
    "player": "Ricky Pearsall",
    "team": "49ers",
    "opponent": "Buccaneers",
    "metric": 13.4
  }
]