[
  {
    "player": "Brock Bowers",
    "team": "Las Vegas Raiders",
    "opponent": "Titans",
    "metric": 30.0,
    "position": "TE"
  },
  {
    "player": "Mason Taylor",
    "team": "New York Jets",
    "opponent": "Broncos",
    "metric": 26.6,
    "position": "TE"
  },
  {
    "player": "Trey McBride",
    "team": "Arizona Cardinals",
    "opponent": "Colts",
    "metric": 25.4,
    "position": "TE"
  },
  {
    "player": "Jake Ferguson",
    "team": "Dallas Cowboys",
    "opponent": "Panthers",
    "metric": 25.3,
    "position": "TE"
  },
  {
    "player": "Cole Kmet",
    "team": "Chicago Bears",
    "opponent": "Commanders",
    "metric": 25.0,
    "position": "TE"
  },
  {
    "player": "Sam LaPorta",
    "team": "Detroit Lions",
    "opponent": "Chiefs",
    "metric": 21.0,
    "position": "TE"
  },
  {
    "player": "Mark Andrews",
    "team": "Baltimore Ravens",
    "opponent": "Rams",
    "metric": 20.8,
    "position": "TE"
  },
  {
    "player": "Kyle Pitts Sr.",
    "team": "Atlanta Falcons",
    "opponent": "Bills",
    "metric": 19.2,
    "position": "TE"
  },
  {
    "player": "David Njoku",
    "team": "Cleveland Browns",
    "opponent": "Steelers",
    "metric": 18.5,
    "position": "TE"
  },
  {
    "player": "Jake Tonges",
    "team": "San Francisco 49ers",
    "opponent": "Buccaneers",
    "metric": 18.2,
    "position": "TE"
  },
  {
    "player": "Travis Kelce",
    "team": "Kansas City Chiefs",
    "opponent": "Lions",
    "metric": 17.1,
    "position": "TE"
  },
  {
    "player": "Albert Okwuegbunam Jr.",
    "team": "Las Vegas Raiders",
    "opponent": "Titans",
    "metric": 16.7,
    "position": "TE"
  },
  {
    "player": "Evan Engram",
    "team": "Denver Broncos",
    "opponent": "Jets",
    "metric": 16.7,
    "position": "TE"
  },
  {
    "player": "AJ Barner",
    "team": "Seattle Seahawks",
    "opponent": "Jaguars",
    "metric": 16.5,
    "position": "TE"
  },
  {
    "player": "Tommy Tremble",
    "team": "Carolina Panthers",
    "opponent": "Cowboys",
    "metric": 16.2,
    "position": "TE"
  },
  {
    "player": "Tyler Warren",
    "team": "Indianapolis Colts",
    "opponent": "Cardinals",
    "metric": 15.8,
    "position": "TE"
  },
  {
    "player": "Harold Fannin Jr.",
    "team": "Cleveland Browns",
    "opponent": "Steelers",
    "metric": 15.1,
    "position": "TE"
  },
  {
    "player": "Dalton Kincaid",
    "team": "Buffalo Bills",
    "opponent": "Falcons",
    "metric": 14.5,
    "position": "TE"
  },
  {
    "player": "Tucker Kraft",
    "team": "Green Bay Packers",
    "opponent": "Bengals",
    "metric": 13.9,
    "position": "TE"
  },
  {
    "player": "Brenton Strange",
    "team": "Jacksonville Jaguars",
    "opponent": "Seahawks",
    "metric": 13.7,
    "position": "TE"
  },
  {
    "player": "Jonnu Smith",
    "team": "Pittsburgh Steelers",
    "opponent": "Browns",
    "metric": 13.6,
    "position": "TE"
  },
  {
    "player": "Chig Okonkwo",
    "team": "Tennessee Titans",
    "opponent": "Raiders",
    "metric": 13.3,
    "position": "TE"
  },
  {
    "player": "Hunter Henry",
    "team": "New England Patriots",
    "opponent": "Saints",
    "metric": 13.0,
    "position": "TE"
  },
  {
    "player": "Cade Otton",
    "team": "Tampa Bay Buccaneers",
    "opponent": "49ers",
    "metric": 12.9,
    "position": "TE"
  },
  {
    "player": "Juwan Johnson",
    "team": "New Orleans Saints",
    "opponent": "Patriots",
    "metric": 12.5,
    "position": "TE"
  },
  {
    "player": "Zach Ertz",
    "team": "Washington Commanders",
    "opponent": "Bears",
    "metric": 10.5,
    "position": "TE"
  },
  {
    "player": "Elijah Arroyo",
    "team": "Seattle Seahawks",
    "opponent": "Jaguars",
    "metric": 9.8,
    "position": "TE"
  },
  {
    "player": "Gunnar Helm",
    "team": "Tennessee Titans",
    "opponent": "Raiders",
    "metric": 8.9,
    "position": "TE"
  },
  {
    "player": "Mike Gesicki",
    "team": "Cincinnati Bengals",
    "opponent": "Packers",
    "metric": 8.5,
    "position": "TE"
  },
  {
    "player": "Ian Thomas",
    "team": "Las Vegas Raiders",
    "opponent": "Titans",
    "metric": 8.3,
    "position": "TE"
  },
  {
    "player": "Mitchell Evans",
    "team": "Carolina Panthers",
    "opponent": "Cowboys",
    "metric": 8.1,
    "position": "TE"
  },
  {
    "player": "Hunter Long",
    "team": "Jacksonville Jaguars",
    "opponent": "Seahawks",
    "metric": 7.0,
    "position": "TE"
  },
  {
    "player": "Elijah Higgins",
    "team": "Arizona Cardinals",
    "opponent": "Colts",
    "metric": 6.7,
    "position": "TE"
  },
  {
    "player": "Jeremy Ruckert",
    "team": "New York Jets",
    "opponent": "Broncos",
    "metric": 6.4,
    "position": "TE"
  },
  {
    "player": "Luke Schoonmaker",
    "team": "Dallas Cowboys",
    "opponent": "Panthers",
    "metric": 6.2,
    "position": "TE"
  },
  {
    "player": "Tyler Conklin",
    "team": "Los Angeles Chargers",
    "opponent": "Dolphins",
    "metric": 6.0,
    "position": "TE"
  },
  {
    "player": "Austin Hooper",
    "team": "New England Patriots",
    "opponent": "Saints",
    "metric": 5.9,
    "position": "TE"
  },
  {
    "player": "Tanner Conner",
    "team": "Miami Dolphins",
    "opponent": "Chargers",
    "metric": 5.9,
    "position": "TE"
  },
  {
    "player": "Dawson Knox",
    "team": "Buffalo Bills",
    "opponent": "Falcons",
    "metric": 5.6,
    "position": "TE"
  },
  {
    "player": "Oronde Gadsden II",
    "team": "Los Angeles Chargers",
    "opponent": "Dolphins",
    "metric": 5.5,
    "position": "TE"
  }
]